zbaseballdata/__init__.py
zbaseballdata/client.py
zbaseballdata/constants.py
zbaseballdata/exceptions.py
zbaseballdata/tests/__init__.py
zbaseballdata-0.1.0.dist-info/METADATA
zbaseballdata-0.1.0.dist-info/WHEEL
zbaseballdata-0.1.0.dist-info/top_level.txt
zbaseballdata-0.1.0.dist-info/RECORD
